{
  "build": {
    "content": [
      {
        "files": [
          "**/*.md",
          "**/*.yml"
        ],
        "exclude": [
          "**/obj/**",
          "**/includes/**",
          "_themes/**",
          "_themes.pdf/**",
          "**/docfx.json",
          "_repo.en-us/**",
          "README.md",
          "LICENSE",
          "LICENSE-CODE",
          "ThirdPartyNotices.md"
        ],
        "src": "."
      }
    ],
    "resource": [
      {
        "files": [
          "**/*.png",
          "**/*.jpg"
        ],
        "exclude": [
          "**/obj/**",
          "**/includes/**",
          "_themes/**",
          "_themes.pdf/**",
          "**/docfx.json",
          "_repo.en-us/**"
        ],
        "src": "."
      }
    ],
    "overwrite": [],
    "externalReference": [],
    "globalMetadata": {
      "breadcrumb_path": "/archive/e2e_archiveDocs_Prod_20210205022647/breadcrumb/e2e_archiveDocs_Prod_20210205022647/toc.json",
      "extendBreadcrumb": true,
      "feedback_system": "None",
      "is_archived": true,
      "is_retired": false,
      "ROBOTS": "NOINDEX,NOFOLLOW",
      "docs_archive": "tool",
      "uhfHeaderId": "MSDocsHeader-Archive"
    },
    "fileMetadata": {},
    "template": [],
    "dest": "archive-template",
    "markdownEngineName": "markdig"
  }
}